alibabacloud_kms20160120/__init__.py
alibabacloud_kms20160120/client.py
alibabacloud_kms20160120/models.py
alibabacloud_kms20160120-2.4.0.dist-info/LICENSE
alibabacloud_kms20160120-2.4.0.dist-info/METADATA
alibabacloud_kms20160120-2.4.0.dist-info/WHEEL
alibabacloud_kms20160120-2.4.0.dist-info/top_level.txt
alibabacloud_kms20160120-2.4.0.dist-info/RECORD
